LICENSE
MANIFEST.in
README.rst
setup.py
django_admin_material/__init__.py
django_admin_material/apps.py
django_admin_material.egg-info/PKG-INFO
django_admin_material.egg-info/SOURCES.txt
django_admin_material.egg-info/dependency_links.txt
django_admin_material.egg-info/requires.txt
django_admin_material.egg-info/top_level.txt
django_admin_material/migrations/__init__.py
django_admin_material/static/.DS_Store
django_admin_material/static/admin/.DS_Store
django_admin_material/static/admin/img/.DS_Store
django_admin_material/static/admin/img/icon-addlink.svg
django_admin_material/static/admin/img/icon-no.svg
django_admin_material/static/admin/img/icon-yes.svg
django_admin_material/static/admin/js/autocomplete.js
django_admin_material/static/django_admin_material/.DS_Store
django_admin_material/static/django_admin_material/css/base.css
django_admin_material/static/django_admin_material/css/forms.css
django_admin_material/static/django_admin_material/css/materialize.min.css
django_admin_material/static/django_admin_material/img/arrow-left.svg
django_admin_material/static/django_admin_material/img/arrow-right.svg
django_admin_material/static/django_admin_material/img/sidebar-background.svg
django_admin_material/static/django_admin_material/img/sidebar-profile.svg
django_admin_material/static/django_admin_material/js/jquery-3.3.1.min.js
django_admin_material/static/django_admin_material/js/materialize.min.js
django_admin_material/templates/admin/actions.html
django_admin_material/templates/admin/base.html
django_admin_material/templates/admin/base_site.html
django_admin_material/templates/admin/change_form.html
django_admin_material/templates/admin/change_form_object_tools.html
django_admin_material/templates/admin/change_list.html
django_admin_material/templates/admin/change_list_object_tools.html
django_admin_material/templates/admin/change_list_results.html
django_admin_material/templates/admin/delete_confirmation.html
django_admin_material/templates/admin/delete_selected_confirmation.html
django_admin_material/templates/admin/filter.html
django_admin_material/templates/admin/index.html
django_admin_material/templates/admin/login.html
django_admin_material/templates/admin/search_form.html
