Metadata-Version: 1.1
Name: django-admin-material
Version: 0.1.0
Summary: A material style interface for Django Admin.
Home-page: https://github.com/lorenzomorandini/django-admin-material
Author: Lorenzo Morandini
Author-email: lorenzo.morandini94@gmail.com
License: MIT
Platform: UNKNOWN
Classifier: Environment :: Web Environment
Classifier: Framework :: Django
Classifier: Intended Audience :: Developers
Classifier: License :: OSI Approved :: MIT License
Classifier: Operating System :: OS Independent
Classifier: Programming Language :: Python
Classifier: Programming Language :: Python :: 3.5
Classifier: Programming Language :: Python :: 3.6
Classifier: Topic :: Internet :: WWW/HTTP
Classifier: Topic :: Internet :: WWW/HTTP :: Dynamic Content
